{"scorpion": {"71": 80}, "hedgehog": {"334": 48}, "crocodile_head": {"49": 42, "50": 6}, "headphone": {"650": 20, "902": 3}, "mandolin": {"402": 18, "546": 6, "420": 7, "889": 3}, "ewer": {"899": 32, "725": 31, "505": 5, "901": 11, "883": 5}, "stop_sign": {"919": 57}, "ant": {"310": 27, "73": 3}, "ferry": {"694": 12, "628": 21, "975": 3, "536": 7, "554": 9}, "butterfly": {"326": 11, "584": 14, "322": 15, "323": 20, "321": 4, "591": 3, "714": 3}, "airplanes": {"404": 641, "895": 96, "908": 31, "812": 17, "856": 5}, "ibis": {"129": 26, "135": 14, "128": 21, "127": 4, "134": 4, "132": 3}, "lobster": {"122": 32, "124": 3}, "buddha": {"708": 36, "921": 6, "406": 11, "857": 5, "562": 3, "715": 7}, "yin_yang": {"746": 8, "485": 3, "999": 4, "600": 4, "722": 4, "700": 10}, "hawksbill": {"33": 67, "36": 9, "34": 19, "983": 3}, "helicopter": {"895": 24, "908": 9, "403": 5, "405": 3, "657": 4, "970": 3, "625": 7, "407": 6}, "pigeon": {"80": 18, "86": 9, "81": 4}, "snoopy": {"549": 8, "591": 8, "917": 3}, "Leopards": {"288": 60, "290": 65, "293": 68}, "pagoda": {"807": 14, "921": 7, "611": 4, "664": 5, "549": 4}, "Faces": {"834": 18, "474": 7, "610": 58, "617": 76, "903": 20, "451": 10, "624": 32, "424": 3, "0": 18, "453": 11, "916": 8, "697": 16, "648": 6, "813": 8, "906": 12, "454": 15, "824": 6, "523": 14, "713": 4, "917": 6, "838": 3, "841": 3, "785": 3, "620": 3, "457": 3}, "cup": {"504": 29, "968": 14}, "Faces_easy": {"903": 37, "610": 50, "617": 92, "789": 3, "906": 26, "624": 29, "454": 5, "834": 46, "0": 23, "453": 7, "788": 5, "697": 8, "474": 3, "419": 5, "785": 3, "916": 4, "652": 7, "457": 8, "523": 3, "575": 3, "917": 3, "678": 5, "865": 4, "683": 3, "918": 3}, "inline_skate": {"774": 5, "770": 6, "584": 3, "615": 4, "502": 3}, "wheelchair": {"870": 32, "612": 9, "830": 6}, "wild_cat": {"288": 11, "281": 5, "290": 6, "285": 5, "287": 6}, "cougar_body": {"286": 42}, "sea_horse": {"329": 6, "390": 3, "126": 4, "973": 5, "111": 6, "65": 3}, "emu": {"9": 45, "355": 3}, "water_lilly": {"868": 9, "58": 4, "985": 15}, "laptop": {"620": 22, "681": 49, "590": 4}, "strawberry": {"949": 28}, "bass": {"389": 25, "0": 12}, "platypus": {"103": 32}, "metronome": {"583": 9, "635": 5}, "ketch": {"914": 62, "780": 46, "484": 4}, "grand_piano": {"579": 91, "526": 3, "881": 4}, "lamp": {"846": 50, "619": 4}, "gramophone": {"606": 4, "632": 3, "566": 5, "846": 6, "513": 9, "818": 4, "807": 3}, "kangaroo": {"104": 80, "331": 3}, "starfish": {"327": 85}, "dalmatian": {"251": 65}, "bonsai": {"738": 109, "789": 3}, "wrench": {"473": 5, "477": 4, "600": 8}, "flamingo_head": {"130": 40}, "umbrella": {"879": 61}, "stegosaurus": {"51": 53}, "revolver": {"763": 78}, "gerenuk": {"352": 13, "353": 13, "286": 3}, "beaver": {"337": 33, "357": 3}, "barrel": {"427": 38, "756": 5}, "anchor": {"730": 3, "584": 3, "600": 8}, "saxophone": {"776": 36}, "dollar_bill": {"481": 4, "549": 22, "446": 3, "692": 6, "916": 5}, "nautilus": {"117": 53}, "elephant": {"101": 17, "386": 21, "385": 20}, "llama": {"355": 74}, "dragonfly": {"319": 43, "623": 3, "584": 4, "549": 3}, "cougar_face": {"286": 62, "292": 3}, "chandelier": {"619": 13, "846": 16, "470": 23, "556": 7, "600": 6, "857": 5, "406": 3, "540": 3, "884": 4, "584": 4}, "Motorbikes": {"665": 634, "573": 8, "671": 14, "670": 105, "518": 12, "535": 6, "870": 7, "817": 6, "866": 3}, "octopus": {"584": 3, "600": 3, "902": 3, "111": 4}, "pyramid": {"442": 6, "853": 5, "682": 3, "980": 5, "970": 5}, "cannon": {"471": 30, "690": 4}, "crayfish": {"122": 17, "124": 34, "303": 3, "314": 3, "123": 4}, "panda": {"388": 23, "850": 5}, "menorah": {"846": 14, "470": 9, "708": 4, "646": 24, "494": 3, "828": 3, "619": 3, "787": 8}, "stapler": {"583": 4, "473": 12, "840": 3, "674": 3}, "flamingo": {"130": 57, "132": 4}, "mayfly": {"318": 21, "319": 5}, "windsor_chair": {"765": 46, "559": 4}, "scissors": {"473": 9, "477": 4, "633": 5, "600": 8}, "crab": {"119": 33, "118": 5, "120": 13, "121": 3, "78": 3}, "car_side": {"468": 14, "864": 21, "656": 12, "660": 8, "436": 15, "751": 7, "627": 16, "475": 4, "817": 3, "704": 10}, "brain": {"956": 14, "936": 4, "109": 19, "328": 4, "452": 3, "916": 4, "584": 4, "996": 3, "993": 7}, "tick": {"78": 48}, "chair": {"857": 7, "559": 14, "765": 26, "423": 5}, "rhino": {"343": 22, "386": 3, "51": 13, "346": 7, "341": 3}, "dolphin": {"150": 3, "2": 9, "4": 16, "149": 4, "148": 12, "3": 12}, "rooster": {"7": 35, "8": 3}, "okapi": {"339": 13, "351": 4, "340": 16, "353": 3}, "pizza": {"963": 27, "964": 5, "551": 3}, "soccer_ball": {"805": 61}, "garfield": {"549": 7, "591": 7, "917": 9}, "ceiling_fan": {"545": 34, "584": 4}, "schooner": {"780": 60}, "joshua_tree": {"972": 6, "978": 15, "975": 12, "351": 10, "970": 3}, "crocodile": {"49": 32, "50": 5, "44": 3}, "brontosaurus": {"51": 21, "354": 5, "47": 3}, "euphonium": {"513": 56, "566": 7}, "minaret": {"812": 5, "623": 4, "807": 6, "583": 7, "798": 4, "769": 5, "657": 6, "744": 5}, "sunflower": {"985": 79}, "BACKGROUND_Google": {"922": 11, "916": 76, "611": 5, "464": 3, "921": 21, "975": 4, "918": 5, "610": 7, "846": 3, "819": 4, "549": 9, "978": 5, "600": 6, "782": 5, "917": 22, "979": 4, "688": 8, "714": 3, "851": 4, "590": 3, "405": 3, "736": 3, "746": 3, "681": 3, "430": 3, "446": 3, "729": 3, "557": 3, "419": 3, "795": 3, "838": 3, "624": 3, "591": 3, "642": 3, "860": 3}, "cellphone": {"531": 3, "761": 9, "778": 3, "487": 17, "590": 6, "713": 3}, "trilobite": {"69": 83}, "lotus": {"868": 3, "985": 22, "738": 15, "584": 5, "883": 9}, "accordion": {"401": 52}, "watch": {"409": 88, "826": 75, "426": 6, "531": 12, "464": 26, "635": 17, "892": 5}, "binocular": {"447": 31}, "camera": {"759": 26, "732": 14}, "electric_guitar": {"546": 50, "402": 11, "596": 4}}